[
  {
    "month": "2006-01-01T00:00:00",
    "crime_category": "Other",
    "count": 11993
  },
  {
    "month": "2006-01-01T00:00:00",
    "crime_category": "Property",
    "count": 4609
  },
  {
    "month": "2006-01-01T00:00:00",
    "crime_category": "Violent",
    "count": 1760
  },
  {
    "month": "2006-02-01T00:00:00",
    "crime_category": "Other",
    "count": 10082
  },
  {
    "month": "2006-02-01T00:00:00",
    "crime_category": "Property",
    "count": 3679
  },
  {
    "month": "2006-02-01T00:00:00",
    "crime_category": "Violent",
    "count": 1403
  },
  {
    "month": "2006-03-01T00:00:00",
    "crime_category": "Other",
    "count": 11674
  },
  {
    "month": "2006-03-01T00:00:00",
    "crime_category": "Property",
    "count": 4399
  },
  {
    "month": "2006-03-01T00:00:00",
    "crime_category": "Violent",
    "count": 1768
  },
  {
    "month": "2006-04-01T00:00:00",
    "crime_category": "Other",
    "count": 12083
  },
  {
    "month": "2006-04-01T00:00:00",
    "crime_category": "Property",
    "count": 4233
  },
  {
    "month": "2006-04-01T00:00:00",
    "crime_category": "Violent",
    "count": 1818
  },
  {
    "month": "2006-05-01T00:00:00",
    "crime_category": "Other",
    "count": 11943
  },
  {
    "month": "2006-05-01T00:00:00",
    "crime_category": "Property",
    "count": 5150
  },
  {
    "month": "2006-05-01T00:00:00",
    "crime_category": "Violent",
    "count": 2014
  },
  {
    "month": "2006-06-01T00:00:00",
    "crime_category": "Other",
    "count": 12440
  },
  {
    "month": "2006-06-01T00:00:00",
    "crime_category": "Property",
    "count": 5015
  },
  {
    "month": "2006-06-01T00:00:00",
    "crime_category": "Violent",
    "count": 1969
  },
  {
    "month": "2006-07-01T00:00:00",
    "crime_category": "Other",
    "count": 12592
  },
  {
    "month": "2006-07-01T00:00:00",
    "crime_category": "Property",
    "count": 5424
  },
  {
    "month": "2006-07-01T00:00:00",
    "crime_category": "Violent",
    "count": 2037
  },
  {
    "month": "2006-08-01T00:00:00",
    "crime_category": "Other",
    "count": 13146
  },
  {
    "month": "2006-08-01T00:00:00",
    "crime_category": "Property",
    "count": 5643
  },
  {
    "month": "2006-08-01T00:00:00",
    "crime_category": "Violent",
    "count": 2041
  },
  {
    "month": "2006-09-01T00:00:00",
    "crime_category": "Other",
    "count": 11291
  },
  {
    "month": "2006-09-01T00:00:00",
    "crime_category": "Property",
    "count": 5437
  },
  {
    "month": "2006-09-01T00:00:00",
    "crime_category": "Violent",
    "count": 1868
  },
  {
    "month": "2006-10-01T00:00:00",
    "crime_category": "Other",
    "count": 12125
  },
  {
    "month": "2006-10-01T00:00:00",
    "crime_category": "Property",
    "count": 5550
  },
  {
    "month": "2006-10-01T00:00:00",
    "crime_category": "Violent",
    "count": 2105
  },
  {
    "month": "2006-11-01T00:00:00",
    "crime_category": "Other",
    "count": 11240
  },
  {
    "month": "2006-11-01T00:00:00",
    "crime_category": "Property",
    "count": 5044
  },
  {
    "month": "2006-11-01T00:00:00",
    "crime_category": "Violent",
    "count": 1946
  },
  {
    "month": "2006-12-01T00:00:00",
    "crime_category": "Other",
    "count": 10918
  },
  {
    "month": "2006-12-01T00:00:00",
    "crime_category": "Property",
    "count": 5064
  },
  {
    "month": "2006-12-01T00:00:00",
    "crime_category": "Violent",
    "count": 1853
  },
  {
    "month": "2007-01-01T00:00:00",
    "crime_category": "Other",
    "count": 10620
  },
  {
    "month": "2007-01-01T00:00:00",
    "crime_category": "Property",
    "count": 4846
  },
  {
    "month": "2007-01-01T00:00:00",
    "crime_category": "Violent",
    "count": 1767
  },
  {
    "month": "2007-02-01T00:00:00",
    "crime_category": "Other",
    "count": 8767
  },
  {
    "month": "2007-02-01T00:00:00",
    "crime_category": "Property",
    "count": 3585
  },
  {
    "month": "2007-02-01T00:00:00",
    "crime_category": "Violent",
    "count": 1322
  },
  {
    "month": "2007-03-01T00:00:00",
    "crime_category": "Other",
    "count": 11640
  },
  {
    "month": "2007-03-01T00:00:00",
    "crime_category": "Property",
    "count": 4450
  },
  {
    "month": "2007-03-01T00:00:00",
    "crime_category": "Violent",
    "count": 1676
  },
  {
    "month": "2007-04-01T00:00:00",
    "crime_category": "Other",
    "count": 11808
  },
  {
    "month": "2007-04-01T00:00:00",
    "crime_category": "Property",
    "count": 4699
  },
  {
    "month": "2007-04-01T00:00:00",
    "crime_category": "Violent",
    "count": 1638
  },
  {
    "month": "2007-05-01T00:00:00",
    "crime_category": "Other",
    "count": 12327
  },
  {
    "month": "2007-05-01T00:00:00",
    "crime_category": "Property",
    "count": 5098
  },
  {
    "month": "2007-05-01T00:00:00",
    "crime_category": "Violent",
    "count": 1934
  },
  {
    "month": "2007-06-01T00:00:00",
    "crime_category": "Other",
    "count": 11290
  },
  {
    "month": "2007-06-01T00:00:00",
    "crime_category": "Property",
    "count": 4945
  },
  {
    "month": "2007-06-01T00:00:00",
    "crime_category": "Violent",
    "count": 1857
  },
  {
    "month": "2007-07-01T00:00:00",
    "crime_category": "Other",
    "count": 11988
  },
  {
    "month": "2007-07-01T00:00:00",
    "crime_category": "Property",
    "count": 5062
  },
  {
    "month": "2007-07-01T00:00:00",
    "crime_category": "Violent",
    "count": 1986
  },
  {
    "month": "2007-08-01T00:00:00",
    "crime_category": "Other",
    "count": 12126
  },
  {
    "month": "2007-08-01T00:00:00",
    "crime_category": "Property",
    "count": 5047
  },
  {
    "month": "2007-08-01T00:00:00",
    "crime_category": "Violent",
    "count": 1777
  },
  {
    "month": "2007-09-01T00:00:00",
    "crime_category": "Other",
    "count": 11420
  },
  {
    "month": "2007-09-01T00:00:00",
    "crime_category": "Property",
    "count": 4656
  },
  {
    "month": "2007-09-01T00:00:00",
    "crime_category": "Violent",
    "count": 1845
  },
  {
    "month": "2007-10-01T00:00:00",
    "crime_category": "Other",
    "count": 11321
  },
  {
    "month": "2007-10-01T00:00:00",
    "crime_category": "Property",
    "count": 5047
  },
  {
    "month": "2007-10-01T00:00:00",
    "crime_category": "Violent",
    "count": 1850
  },
  {
    "month": "2007-11-01T00:00:00",
    "crime_category": "Other",
    "count": 9999
  },
  {
    "month": "2007-11-01T00:00:00",
    "crime_category": "Property",
    "count": 4779
  },
  {
    "month": "2007-11-01T00:00:00",
    "crime_category": "Violent",
    "count": 1601
  },
  {
    "month": "2007-12-01T00:00:00",
    "crime_category": "Other",
    "count": 10325
  },
  {
    "month": "2007-12-01T00:00:00",
    "crime_category": "Property",
    "count": 4742
  },
  {
    "month": "2007-12-01T00:00:00",
    "crime_category": "Violent",
    "count": 1556
  },
  {
    "month": "2008-01-01T00:00:00",
    "crime_category": "Other",
    "count": 10761
  },
  {
    "month": "2008-01-01T00:00:00",
    "crime_category": "Property",
    "count": 4615
  },
  {
    "month": "2008-01-01T00:00:00",
    "crime_category": "Violent",
    "count": 1549
  },
  {
    "month": "2008-02-01T00:00:00",
    "crime_category": "Other",
    "count": 10173
  },
  {
    "month": "2008-02-01T00:00:00",
    "crime_category": "Property",
    "count": 3968
  },
  {
    "month": "2008-02-01T00:00:00",
    "crime_category": "Violent",
    "count": 1406
  },
  {
    "month": "2008-03-01T00:00:00",
    "crime_category": "Other",
    "count": 12355
  },
  {
    "month": "2008-03-01T00:00:00",
    "crime_category": "Property",
    "count": 4375
  },
  {
    "month": "2008-03-01T00:00:00",
    "crime_category": "Violent",
    "count": 1561
  },
  {
    "month": "2008-04-01T00:00:00",
    "crime_category": "Other",
    "count": 12358
  },
  {
    "month": "2008-04-01T00:00:00",
    "crime_category": "Property",
    "count": 4627
  },
  {
    "month": "2008-04-01T00:00:00",
    "crime_category": "Violent",
    "count": 1674
  },
  {
    "month": "2008-05-01T00:00:00",
    "crime_category": "Other",
    "count": 11595
  },
  {
    "month": "2008-05-01T00:00:00",
    "crime_category": "Property",
    "count": 4589
  },
  {
    "month": "2008-05-01T00:00:00",
    "crime_category": "Violent",
    "count": 1685
  },
  {
    "month": "2008-06-01T00:00:00",
    "crime_category": "Other",
    "count": 12231
  },
  {
    "month": "2008-06-01T00:00:00",
    "crime_category": "Property",
    "count": 4999
  },
  {
    "month": "2008-06-01T00:00:00",
    "crime_category": "Violent",
    "count": 1862
  },
  {
    "month": "2008-07-01T00:00:00",
    "crime_category": "Other",
    "count": 12605
  },
  {
    "month": "2008-07-01T00:00:00",
    "crime_category": "Property",
    "count": 5263
  },
  {
    "month": "2008-07-01T00:00:00",
    "crime_category": "Violent",
    "count": 1881
  },
  {
    "month": "2008-08-01T00:00:00",
    "crime_category": "Other",
    "count": 12773
  },
  {
    "month": "2008-08-01T00:00:00",
    "crime_category": "Property",
    "count": 5297
  },
  {
    "month": "2008-08-01T00:00:00",
    "crime_category": "Violent",
    "count": 1860
  },
  {
    "month": "2008-09-01T00:00:00",
    "crime_category": "Other",
    "count": 10238
  },
  {
    "month": "2008-09-01T00:00:00",
    "crime_category": "Property",
    "count": 5057
  },
  {
    "month": "2008-09-01T00:00:00",
    "crime_category": "Violent",
    "count": 1821
  },
  {
    "month": "2008-10-01T00:00:00",
    "crime_category": "Other",
    "count": 10432
  },
  {
    "month": "2008-10-01T00:00:00",
    "crime_category": "Property",
    "count": 4979
  },
  {
    "month": "2008-10-01T00:00:00",
    "crime_category": "Violent",
    "count": 1946
  },
  {
    "month": "2008-11-01T00:00:00",
    "crime_category": "Other",
    "count": 9301
  },
  {
    "month": "2008-11-01T00:00:00",
    "crime_category": "Property",
    "count": 4575
  },
  {
    "month": "2008-11-01T00:00:00",
    "crime_category": "Violent",
    "count": 1669
  },
  {
    "month": "2008-12-01T00:00:00",
    "crime_category": "Other",
    "count": 9499
  },
  {
    "month": "2008-12-01T00:00:00",
    "crime_category": "Property",
    "count": 4547
  },
  {
    "month": "2008-12-01T00:00:00",
    "crime_category": "Violent",
    "count": 1766
  },
  {
    "month": "2009-01-01T00:00:00",
    "crime_category": "Other",
    "count": 9315
  },
  {
    "month": "2009-01-01T00:00:00",
    "crime_category": "Property",
    "count": 3880
  },
  {
    "month": "2009-01-01T00:00:00",
    "crime_category": "Violent",
    "count": 1576
  },
  {
    "month": "2009-02-01T00:00:00",
    "crime_category": "Other",
    "count": 9067
  },
  {
    "month": "2009-02-01T00:00:00",
    "crime_category": "Property",
    "count": 3352
  },
  {
    "month": "2009-02-01T00:00:00",
    "crime_category": "Violent",
    "count": 1283
  },
  {
    "month": "2009-03-01T00:00:00",
    "crime_category": "Other",
    "count": 11299
  },
  {
    "month": "2009-03-01T00:00:00",
    "crime_category": "Property",
    "count": 3826
  },
  {
    "month": "2009-03-01T00:00:00",
    "crime_category": "Violent",
    "count": 1501
  },
  {
    "month": "2009-04-01T00:00:00",
    "crime_category": "Other",
    "count": 11614
  },
  {
    "month": "2009-04-01T00:00:00",
    "crime_category": "Property",
    "count": 3906
  },
  {
    "month": "2009-04-01T00:00:00",
    "crime_category": "Violent",
    "count": 1557
  },
  {
    "month": "2009-05-01T00:00:00",
    "crime_category": "Other",
    "count": 11613
  },
  {
    "month": "2009-05-01T00:00:00",
    "crime_category": "Property",
    "count": 4302
  },
  {
    "month": "2009-05-01T00:00:00",
    "crime_category": "Violent",
    "count": 1700
  },
  {
    "month": "2009-06-01T00:00:00",
    "crime_category": "Other",
    "count": 11577
  },
  {
    "month": "2009-06-01T00:00:00",
    "crime_category": "Property",
    "count": 4401
  },
  {
    "month": "2009-06-01T00:00:00",
    "crime_category": "Violent",
    "count": 1606
  },
  {
    "month": "2009-07-01T00:00:00",
    "crime_category": "Other",
    "count": 11683
  },
  {
    "month": "2009-07-01T00:00:00",
    "crime_category": "Property",
    "count": 4504
  },
  {
    "month": "2009-07-01T00:00:00",
    "crime_category": "Violent",
    "count": 1714
  },
  {
    "month": "2009-08-01T00:00:00",
    "crime_category": "Other",
    "count": 11422
  },
  {
    "month": "2009-08-01T00:00:00",
    "crime_category": "Property",
    "count": 4910
  },
  {
    "month": "2009-08-01T00:00:00",
    "crime_category": "Violent",
    "count": 1802
  },
  {
    "month": "2009-09-01T00:00:00",
    "crime_category": "Other",
    "count": 9800
  },
  {
    "month": "2009-09-01T00:00:00",
    "crime_category": "Property",
    "count": 4738
  },
  {
    "month": "2009-09-01T00:00:00",
    "crime_category": "Violent",
    "count": 1688
  },
  {
    "month": "2009-10-01T00:00:00",
    "crime_category": "Other",
    "count": 9854
  },
  {
    "month": "2009-10-01T00:00:00",
    "crime_category": "Property",
    "count": 4768
  },
  {
    "month": "2009-10-01T00:00:00",
    "crime_category": "Violent",
    "count": 1601
  },
  {
    "month": "2009-11-01T00:00:00",
    "crime_category": "Other",
    "count": 9336
  },
  {
    "month": "2009-11-01T00:00:00",
    "crime_category": "Property",
    "count": 4453
  },
  {
    "month": "2009-11-01T00:00:00",
    "crime_category": "Violent",
    "count": 1500
  },
  {
    "month": "2009-12-01T00:00:00",
    "crime_category": "Other",
    "count": 8441
  },
  {
    "month": "2009-12-01T00:00:00",
    "crime_category": "Property",
    "count": 4195
  },
  {
    "month": "2009-12-01T00:00:00",
    "crime_category": "Violent",
    "count": 1492
  },
  {
    "month": "2010-01-01T00:00:00",
    "crime_category": "Other",
    "count": 9197
  },
  {
    "month": "2010-01-01T00:00:00",
    "crime_category": "Property",
    "count": 4310
  },
  {
    "month": "2010-01-01T00:00:00",
    "crime_category": "Violent",
    "count": 1432
  },
  {
    "month": "2010-02-01T00:00:00",
    "crime_category": "Other",
    "count": 7820
  },
  {
    "month": "2010-02-01T00:00:00",
    "crime_category": "Property",
    "count": 2973
  },
  {
    "month": "2010-02-01T00:00:00",
    "crime_category": "Violent",
    "count": 1026
  },
  {
    "month": "2010-03-01T00:00:00",
    "crime_category": "Other",
    "count": 10423
  },
  {
    "month": "2010-03-01T00:00:00",
    "crime_category": "Property",
    "count": 4294
  },
  {
    "month": "2010-03-01T00:00:00",
    "crime_category": "Violent",
    "count": 1421
  },
  {
    "month": "2010-04-01T00:00:00",
    "crime_category": "Other",
    "count": 10489
  },
  {
    "month": "2010-04-01T00:00:00",
    "crime_category": "Property",
    "count": 4495
  },
  {
    "month": "2010-04-01T00:00:00",
    "crime_category": "Violent",
    "count": 1597
  },
  {
    "month": "2010-05-01T00:00:00",
    "crime_category": "Other",
    "count": 11190
  },
  {
    "month": "2010-05-01T00:00:00",
    "crime_category": "Property",
    "count": 5029
  },
  {
    "month": "2010-05-01T00:00:00",
    "crime_category": "Violent",
    "count": 1703
  },
  {
    "month": "2010-06-01T00:00:00",
    "crime_category": "Other",
    "count": 10913
  },
  {
    "month": "2010-06-01T00:00:00",
    "crime_category": "Property",
    "count": 5207
  },
  {
    "month": "2010-06-01T00:00:00",
    "crime_category": "Violent",
    "count": 1570
  },
  {
    "month": "2010-07-01T00:00:00",
    "crime_category": "Other",
    "count": 11184
  },
  {
    "month": "2010-07-01T00:00:00",
    "crime_category": "Property",
    "count": 5335
  },
  {
    "month": "2010-07-01T00:00:00",
    "crime_category": "Violent",
    "count": 1741
  },
  {
    "month": "2010-08-01T00:00:00",
    "crime_category": "Other",
    "count": 11495
  },
  {
    "month": "2010-08-01T00:00:00",
    "crime_category": "Property",
    "count": 5498
  },
  {
    "month": "2010-08-01T00:00:00",
    "crime_category": "Violent",
    "count": 1708
  },
  {
    "month": "2010-09-01T00:00:00",
    "crime_category": "Other",
    "count": 9552
  },
  {
    "month": "2010-09-01T00:00:00",
    "crime_category": "Property",
    "count": 5279
  },
  {
    "month": "2010-09-01T00:00:00",
    "crime_category": "Violent",
    "count": 1679
  },
  {
    "month": "2010-10-01T00:00:00",
    "crime_category": "Other",
    "count": 9640
  },
  {
    "month": "2010-10-01T00:00:00",
    "crime_category": "Property",
    "count": 5376
  },
  {
    "month": "2010-10-01T00:00:00",
    "crime_category": "Violent",
    "count": 1630
  },
  {
    "month": "2010-11-01T00:00:00",
    "crime_category": "Other",
    "count": 9114
  },
  {
    "month": "2010-11-01T00:00:00",
    "crime_category": "Property",
    "count": 4922
  },
  {
    "month": "2010-11-01T00:00:00",
    "crime_category": "Violent",
    "count": 1592
  },
  {
    "month": "2010-12-01T00:00:00",
    "crime_category": "Other",
    "count": 7639
  },
  {
    "month": "2010-12-01T00:00:00",
    "crime_category": "Property",
    "count": 4485
  },
  {
    "month": "2010-12-01T00:00:00",
    "crime_category": "Violent",
    "count": 1350
  },
  {
    "month": "2011-01-01T00:00:00",
    "crime_category": "Other",
    "count": 7667
  },
  {
    "month": "2011-01-01T00:00:00",
    "crime_category": "Property",
    "count": 4312
  },
  {
    "month": "2011-01-01T00:00:00",
    "crime_category": "Violent",
    "count": 1335
  },
  {
    "month": "2011-02-01T00:00:00",
    "crime_category": "Other",
    "count": 8510
  },
  {
    "month": "2011-02-01T00:00:00",
    "crime_category": "Property",
    "count": 3774
  },
  {
    "month": "2011-02-01T00:00:00",
    "crime_category": "Violent",
    "count": 1144
  },
  {
    "month": "2011-03-01T00:00:00",
    "crime_category": "Other",
    "count": 10506
  },
  {
    "month": "2011-03-01T00:00:00",
    "crime_category": "Property",
    "count": 4387
  },
  {
    "month": "2011-03-01T00:00:00",
    "crime_category": "Violent",
    "count": 1363
  },
  {
    "month": "2011-04-01T00:00:00",
    "crime_category": "Other",
    "count": 10369
  },
  {
    "month": "2011-04-01T00:00:00",
    "crime_category": "Property",
    "count": 4538
  },
  {
    "month": "2011-04-01T00:00:00",
    "crime_category": "Violent",
    "count": 1582
  },
  {
    "month": "2011-05-01T00:00:00",
    "crime_category": "Other",
    "count": 10283
  },
  {
    "month": "2011-05-01T00:00:00",
    "crime_category": "Property",
    "count": 5075
  },
  {
    "month": "2011-05-01T00:00:00",
    "crime_category": "Violent",
    "count": 1639
  },
  {
    "month": "2011-06-01T00:00:00",
    "crime_category": "Other",
    "count": 10652
  },
  {
    "month": "2011-06-01T00:00:00",
    "crime_category": "Property",
    "count": 5226
  },
  {
    "month": "2011-06-01T00:00:00",
    "crime_category": "Violent",
    "count": 1608
  },
  {
    "month": "2011-07-01T00:00:00",
    "crime_category": "Other",
    "count": 10308
  },
  {
    "month": "2011-07-01T00:00:00",
    "crime_category": "Property",
    "count": 5464
  },
  {
    "month": "2011-07-01T00:00:00",
    "crime_category": "Violent",
    "count": 1687
  },
  {
    "month": "2011-08-01T00:00:00",
    "crime_category": "Other",
    "count": 10403
  },
  {
    "month": "2011-08-01T00:00:00",
    "crime_category": "Property",
    "count": 5464
  },
  {
    "month": "2011-08-01T00:00:00",
    "crime_category": "Violent",
    "count": 1559
  },
  {
    "month": "2011-09-01T00:00:00",
    "crime_category": "Other",
    "count": 9368
  },
  {
    "month": "2011-09-01T00:00:00",
    "crime_category": "Property",
    "count": 5436
  },
  {
    "month": "2011-09-01T00:00:00",
    "crime_category": "Violent",
    "count": 1686
  },
  {
    "month": "2011-10-01T00:00:00",
    "crime_category": "Other",
    "count": 8742
  },
  {
    "month": "2011-10-01T00:00:00",
    "crime_category": "Property",
    "count": 5266
  },
  {
    "month": "2011-10-01T00:00:00",
    "crime_category": "Violent",
    "count": 1549
  },
  {
    "month": "2011-11-01T00:00:00",
    "crime_category": "Other",
    "count": 8363
  },
  {
    "month": "2011-11-01T00:00:00",
    "crime_category": "Property",
    "count": 5044
  },
  {
    "month": "2011-11-01T00:00:00",
    "crime_category": "Violent",
    "count": 1498
  },
  {
    "month": "2011-12-01T00:00:00",
    "crime_category": "Other",
    "count": 7995
  },
  {
    "month": "2011-12-01T00:00:00",
    "crime_category": "Property",
    "count": 4875
  },
  {
    "month": "2011-12-01T00:00:00",
    "crime_category": "Violent",
    "count": 1533
  },
  {
    "month": "2012-01-01T00:00:00",
    "crime_category": "Other",
    "count": 9000
  },
  {
    "month": "2012-01-01T00:00:00",
    "crime_category": "Property",
    "count": 4492
  },
  {
    "month": "2012-01-01T00:00:00",
    "crime_category": "Violent",
    "count": 1394
  },
  {
    "month": "2012-02-01T00:00:00",
    "crime_category": "Other",
    "count": 9530
  },
  {
    "month": "2012-02-01T00:00:00",
    "crime_category": "Property",
    "count": 3873
  },
  {
    "month": "2012-02-01T00:00:00",
    "crime_category": "Violent",
    "count": 1275
  },
  {
    "month": "2012-03-01T00:00:00",
    "crime_category": "Other",
    "count": 10722
  },
  {
    "month": "2012-03-01T00:00:00",
    "crime_category": "Property",
    "count": 4017
  },
  {
    "month": "2012-03-01T00:00:00",
    "crime_category": "Violent",
    "count": 1402
  },
  {
    "month": "2012-04-01T00:00:00",
    "crime_category": "Other",
    "count": 10305
  },
  {
    "month": "2012-04-01T00:00:00",
    "crime_category": "Property",
    "count": 4280
  },
  {
    "month": "2012-04-01T00:00:00",
    "crime_category": "Violent",
    "count": 1458
  },
  {
    "month": "2012-05-01T00:00:00",
    "crime_category": "Other",
    "count": 11042
  },
  {
    "month": "2012-05-01T00:00:00",
    "crime_category": "Property",
    "count": 4528
  },
  {
    "month": "2012-05-01T00:00:00",
    "crime_category": "Violent",
    "count": 1592
  },
  {
    "month": "2012-06-01T00:00:00",
    "crime_category": "Other",
    "count": 10757
  },
  {
    "month": "2012-06-01T00:00:00",
    "crime_category": "Property",
    "count": 4527
  },
  {
    "month": "2012-06-01T00:00:00",
    "crime_category": "Violent",
    "count": 1548
  },
  {
    "month": "2012-07-01T00:00:00",
    "crime_category": "Other",
    "count": 10416
  },
  {
    "month": "2012-07-01T00:00:00",
    "crime_category": "Property",
    "count": 4576
  },
  {
    "month": "2012-07-01T00:00:00",
    "crime_category": "Violent",
    "count": 1725
  },
  {
    "month": "2012-08-01T00:00:00",
    "crime_category": "Other",
    "count": 10220
  },
  {
    "month": "2012-08-01T00:00:00",
    "crime_category": "Property",
    "count": 5084
  },
  {
    "month": "2012-08-01T00:00:00",
    "crime_category": "Violent",
    "count": 1686
  },
  {
    "month": "2012-09-01T00:00:00",
    "crime_category": "Other",
    "count": 9612
  },
  {
    "month": "2012-09-01T00:00:00",
    "crime_category": "Property",
    "count": 4991
  },
  {
    "month": "2012-09-01T00:00:00",
    "crime_category": "Violent",
    "count": 1603
  },
  {
    "month": "2012-10-01T00:00:00",
    "crime_category": "Other",
    "count": 9741
  },
  {
    "month": "2012-10-01T00:00:00",
    "crime_category": "Property",
    "count": 4843
  },
  {
    "month": "2012-10-01T00:00:00",
    "crime_category": "Violent",
    "count": 1495
  },
  {
    "month": "2012-11-01T00:00:00",
    "crime_category": "Other",
    "count": 8274
  },
  {
    "month": "2012-11-01T00:00:00",
    "crime_category": "Property",
    "count": 4347
  },
  {
    "month": "2012-11-01T00:00:00",
    "crime_category": "Violent",
    "count": 1334
  },
  {
    "month": "2012-12-01T00:00:00",
    "crime_category": "Other",
    "count": 8266
  },
  {
    "month": "2012-12-01T00:00:00",
    "crime_category": "Property",
    "count": 4166
  },
  {
    "month": "2012-12-01T00:00:00",
    "crime_category": "Violent",
    "count": 1344
  },
  {
    "month": "2013-01-01T00:00:00",
    "crime_category": "Other",
    "count": 8539
  },
  {
    "month": "2013-01-01T00:00:00",
    "crime_category": "Property",
    "count": 3878
  },
  {
    "month": "2013-01-01T00:00:00",
    "crime_category": "Violent",
    "count": 1306
  },
  {
    "month": "2013-02-01T00:00:00",
    "crime_category": "Other",
    "count": 7962
  },
  {
    "month": "2013-02-01T00:00:00",
    "crime_category": "Property",
    "count": 3246
  },
  {
    "month": "2013-02-01T00:00:00",
    "crime_category": "Violent",
    "count": 1107
  },
  {
    "month": "2013-03-01T00:00:00",
    "crime_category": "Other",
    "count": 9823
  },
  {
    "month": "2013-03-01T00:00:00",
    "crime_category": "Property",
    "count": 3521
  },
  {
    "month": "2013-03-01T00:00:00",
    "crime_category": "Violent",
    "count": 1345
  },
  {
    "month": "2013-04-01T00:00:00",
    "crime_category": "Other",
    "count": 9815
  },
  {
    "month": "2013-04-01T00:00:00",
    "crime_category": "Property",
    "count": 3753
  },
  {
    "month": "2013-04-01T00:00:00",
    "crime_category": "Violent",
    "count": 1441
  },
  {
    "month": "2013-05-01T00:00:00",
    "crime_category": "Other",
    "count": 10596
  },
  {
    "month": "2013-05-01T00:00:00",
    "crime_category": "Property",
    "count": 4222
  },
  {
    "month": "2013-05-01T00:00:00",
    "crime_category": "Violent",
    "count": 1535
  },
  {
    "month": "2013-06-01T00:00:00",
    "crime_category": "Other",
    "count": 10205
  },
  {
    "month": "2013-06-01T00:00:00",
    "crime_category": "Property",
    "count": 4501
  },
  {
    "month": "2013-06-01T00:00:00",
    "crime_category": "Violent",
    "count": 1455
  },
  {
    "month": "2013-07-01T00:00:00",
    "crime_category": "Other",
    "count": 10178
  },
  {
    "month": "2013-07-01T00:00:00",
    "crime_category": "Property",
    "count": 4872
  },
  {
    "month": "2013-07-01T00:00:00",
    "crime_category": "Violent",
    "count": 1475
  },
  {
    "month": "2013-08-01T00:00:00",
    "crime_category": "Other",
    "count": 10303
  },
  {
    "month": "2013-08-01T00:00:00",
    "crime_category": "Property",
    "count": 4982
  },
  {
    "month": "2013-08-01T00:00:00",
    "crime_category": "Violent",
    "count": 1573
  },
  {
    "month": "2013-09-01T00:00:00",
    "crime_category": "Other",
    "count": 9235
  },
  {
    "month": "2013-09-01T00:00:00",
    "crime_category": "Property",
    "count": 4604
  },
  {
    "month": "2013-09-01T00:00:00",
    "crime_category": "Violent",
    "count": 1488
  },
  {
    "month": "2013-10-01T00:00:00",
    "crime_category": "Other",
    "count": 9739
  },
  {
    "month": "2013-10-01T00:00:00",
    "crime_category": "Property",
    "count": 4632
  },
  {
    "month": "2013-10-01T00:00:00",
    "crime_category": "Violent",
    "count": 1537
  },
  {
    "month": "2013-11-01T00:00:00",
    "crime_category": "Other",
    "count": 8421
  },
  {
    "month": "2013-11-01T00:00:00",
    "crime_category": "Property",
    "count": 4002
  },
  {
    "month": "2013-11-01T00:00:00",
    "crime_category": "Violent",
    "count": 1463
  },
  {
    "month": "2013-12-01T00:00:00",
    "crime_category": "Other",
    "count": 7412
  },
  {
    "month": "2013-12-01T00:00:00",
    "crime_category": "Property",
    "count": 3786
  },
  {
    "month": "2013-12-01T00:00:00",
    "crime_category": "Violent",
    "count": 1292
  },
  {
    "month": "2014-01-01T00:00:00",
    "crime_category": "Other",
    "count": 7124
  },
  {
    "month": "2014-01-01T00:00:00",
    "crime_category": "Property",
    "count": 3399
  },
  {
    "month": "2014-01-01T00:00:00",
    "crime_category": "Violent",
    "count": 1230
  },
  {
    "month": "2014-02-01T00:00:00",
    "crime_category": "Other",
    "count": 6925
  },
  {
    "month": "2014-02-01T00:00:00",
    "crime_category": "Property",
    "count": 2839
  },
  {
    "month": "2014-02-01T00:00:00",
    "crime_category": "Violent",
    "count": 1014
  },
  {
    "month": "2014-03-01T00:00:00",
    "crime_category": "Other",
    "count": 8901
  },
  {
    "month": "2014-03-01T00:00:00",
    "crime_category": "Property",
    "count": 3422
  },
  {
    "month": "2014-03-01T00:00:00",
    "crime_category": "Violent",
    "count": 1202
  },
  {
    "month": "2014-04-01T00:00:00",
    "crime_category": "Other",
    "count": 10165
  },
  {
    "month": "2014-04-01T00:00:00",
    "crime_category": "Property",
    "count": 3772
  },
  {
    "month": "2014-04-01T00:00:00",
    "crime_category": "Violent",
    "count": 1260
  },
  {
    "month": "2014-05-01T00:00:00",
    "crime_category": "Other",
    "count": 10584
  },
  {
    "month": "2014-05-01T00:00:00",
    "crime_category": "Property",
    "count": 4661
  },
  {
    "month": "2014-05-01T00:00:00",
    "crime_category": "Violent",
    "count": 1486
  },
  {
    "month": "2014-06-01T00:00:00",
    "crime_category": "Other",
    "count": 10186
  },
  {
    "month": "2014-06-01T00:00:00",
    "crime_category": "Property",
    "count": 4529
  },
  {
    "month": "2014-06-01T00:00:00",
    "crime_category": "Violent",
    "count": 1460
  },
  {
    "month": "2014-07-01T00:00:00",
    "crime_category": "Other",
    "count": 10946
  },
  {
    "month": "2014-07-01T00:00:00",
    "crime_category": "Property",
    "count": 4907
  },
  {
    "month": "2014-07-01T00:00:00",
    "crime_category": "Violent",
    "count": 1419
  },
  {
    "month": "2014-08-01T00:00:00",
    "crime_category": "Other",
    "count": 9959
  },
  {
    "month": "2014-08-01T00:00:00",
    "crime_category": "Property",
    "count": 4677
  },
  {
    "month": "2014-08-01T00:00:00",
    "crime_category": "Violent",
    "count": 1439
  },
  {
    "month": "2014-09-01T00:00:00",
    "crime_category": "Other",
    "count": 10477
  },
  {
    "month": "2014-09-01T00:00:00",
    "crime_category": "Property",
    "count": 4327
  },
  {
    "month": "2014-09-01T00:00:00",
    "crime_category": "Violent",
    "count": 1355
  },
  {
    "month": "2014-10-01T00:00:00",
    "crime_category": "Other",
    "count": 10809
  },
  {
    "month": "2014-10-01T00:00:00",
    "crime_category": "Property",
    "count": 4780
  },
  {
    "month": "2014-10-01T00:00:00",
    "crime_category": "Violent",
    "count": 1407
  },
  {
    "month": "2014-11-01T00:00:00",
    "crime_category": "Other",
    "count": 9162
  },
  {
    "month": "2014-11-01T00:00:00",
    "crime_category": "Property",
    "count": 3891
  },
  {
    "month": "2014-11-01T00:00:00",
    "crime_category": "Violent",
    "count": 1247
  },
  {
    "month": "2014-12-01T00:00:00",
    "crime_category": "Other",
    "count": 8225
  },
  {
    "month": "2014-12-01T00:00:00",
    "crime_category": "Property",
    "count": 4059
  },
  {
    "month": "2014-12-01T00:00:00",
    "crime_category": "Violent",
    "count": 1378
  },
  {
    "month": "2015-01-01T00:00:00",
    "crime_category": "Other",
    "count": 8326
  },
  {
    "month": "2015-01-01T00:00:00",
    "crime_category": "Property",
    "count": 3630
  },
  {
    "month": "2015-01-01T00:00:00",
    "crime_category": "Violent",
    "count": 1221
  },
  {
    "month": "2015-02-01T00:00:00",
    "crime_category": "Other",
    "count": 8007
  },
  {
    "month": "2015-02-01T00:00:00",
    "crime_category": "Property",
    "count": 2804
  },
  {
    "month": "2015-02-01T00:00:00",
    "crime_category": "Violent",
    "count": 979
  },
  {
    "month": "2015-03-01T00:00:00",
    "crime_category": "Other",
    "count": 9339
  },
  {
    "month": "2015-03-01T00:00:00",
    "crime_category": "Property",
    "count": 3419
  },
  {
    "month": "2015-03-01T00:00:00",
    "crime_category": "Violent",
    "count": 1150
  },
  {
    "month": "2015-04-01T00:00:00",
    "crime_category": "Other",
    "count": 11299
  },
  {
    "month": "2015-04-01T00:00:00",
    "crime_category": "Property",
    "count": 3685
  },
  {
    "month": "2015-04-01T00:00:00",
    "crime_category": "Violent",
    "count": 1303
  },
  {
    "month": "2015-05-01T00:00:00",
    "crime_category": "Other",
    "count": 10826
  },
  {
    "month": "2015-05-01T00:00:00",
    "crime_category": "Property",
    "count": 4130
  },
  {
    "month": "2015-05-01T00:00:00",
    "crime_category": "Violent",
    "count": 1558
  },
  {
    "month": "2015-06-01T00:00:00",
    "crime_category": "Other",
    "count": 10221
  },
  {
    "month": "2015-06-01T00:00:00",
    "crime_category": "Property",
    "count": 4151
  },
  {
    "month": "2015-06-01T00:00:00",
    "crime_category": "Violent",
    "count": 1420
  },
  {
    "month": "2015-07-01T00:00:00",
    "crime_category": "Other",
    "count": 10803
  },
  {
    "month": "2015-07-01T00:00:00",
    "crime_category": "Property",
    "count": 4261
  },
  {
    "month": "2015-07-01T00:00:00",
    "crime_category": "Violent",
    "count": 1525
  },
  {
    "month": "2015-08-01T00:00:00",
    "crime_category": "Other",
    "count": 10797
  },
  {
    "month": "2015-08-01T00:00:00",
    "crime_category": "Property",
    "count": 4463
  },
  {
    "month": "2015-08-01T00:00:00",
    "crime_category": "Violent",
    "count": 1521
  },
  {
    "month": "2015-09-01T00:00:00",
    "crime_category": "Other",
    "count": 9225
  },
  {
    "month": "2015-09-01T00:00:00",
    "crime_category": "Property",
    "count": 4102
  },
  {
    "month": "2015-09-01T00:00:00",
    "crime_category": "Violent",
    "count": 1513
  },
  {
    "month": "2015-10-01T00:00:00",
    "crime_category": "Other",
    "count": 9352
  },
  {
    "month": "2015-10-01T00:00:00",
    "crime_category": "Property",
    "count": 3933
  },
  {
    "month": "2015-10-01T00:00:00",
    "crime_category": "Violent",
    "count": 1352
  },
  {
    "month": "2015-11-01T00:00:00",
    "crime_category": "Other",
    "count": 8346
  },
  {
    "month": "2015-11-01T00:00:00",
    "crime_category": "Property",
    "count": 3655
  },
  {
    "month": "2015-11-01T00:00:00",
    "crime_category": "Violent",
    "count": 1311
  },
  {
    "month": "2015-12-01T00:00:00",
    "crime_category": "Other",
    "count": 7986
  },
  {
    "month": "2015-12-01T00:00:00",
    "crime_category": "Property",
    "count": 3870
  },
  {
    "month": "2015-12-01T00:00:00",
    "crime_category": "Violent",
    "count": 1285
  },
  {
    "month": "2016-01-01T00:00:00",
    "crime_category": "Other",
    "count": 7026
  },
  {
    "month": "2016-01-01T00:00:00",
    "crime_category": "Property",
    "count": 3206
  },
  {
    "month": "2016-01-01T00:00:00",
    "crime_category": "Violent",
    "count": 1159
  },
  {
    "month": "2016-02-01T00:00:00",
    "crime_category": "Other",
    "count": 7614
  },
  {
    "month": "2016-02-01T00:00:00",
    "crime_category": "Property",
    "count": 3067
  },
  {
    "month": "2016-02-01T00:00:00",
    "crime_category": "Violent",
    "count": 984
  },
  {
    "month": "2016-03-01T00:00:00",
    "crime_category": "Other",
    "count": 8623
  },
  {
    "month": "2016-03-01T00:00:00",
    "crime_category": "Property",
    "count": 3537
  },
  {
    "month": "2016-03-01T00:00:00",
    "crime_category": "Violent",
    "count": 1213
  },
  {
    "month": "2016-04-01T00:00:00",
    "crime_category": "Other",
    "count": 8893
  },
  {
    "month": "2016-04-01T00:00:00",
    "crime_category": "Property",
    "count": 3543
  },
  {
    "month": "2016-04-01T00:00:00",
    "crime_category": "Violent",
    "count": 1218
  },
  {
    "month": "2016-05-01T00:00:00",
    "crime_category": "Other",
    "count": 9509
  },
  {
    "month": "2016-05-01T00:00:00",
    "crime_category": "Property",
    "count": 3831
  },
  {
    "month": "2016-05-01T00:00:00",
    "crime_category": "Violent",
    "count": 1406
  },
  {
    "month": "2016-06-01T00:00:00",
    "crime_category": "Other",
    "count": 9454
  },
  {
    "month": "2016-06-01T00:00:00",
    "crime_category": "Property",
    "count": 3932
  },
  {
    "month": "2016-06-01T00:00:00",
    "crime_category": "Violent",
    "count": 1378
  },
  {
    "month": "2016-07-01T00:00:00",
    "crime_category": "Other",
    "count": 7812
  },
  {
    "month": "2016-07-01T00:00:00",
    "crime_category": "Property",
    "count": 4230
  },
  {
    "month": "2016-07-01T00:00:00",
    "crime_category": "Violent",
    "count": 1425
  },
  {
    "month": "2016-08-01T00:00:00",
    "crime_category": "Other",
    "count": 8928
  },
  {
    "month": "2016-08-01T00:00:00",
    "crime_category": "Property",
    "count": 4607
  },
  {
    "month": "2016-08-01T00:00:00",
    "crime_category": "Violent",
    "count": 1450
  },
  {
    "month": "2016-09-01T00:00:00",
    "crime_category": "Other",
    "count": 8352
  },
  {
    "month": "2016-09-01T00:00:00",
    "crime_category": "Property",
    "count": 4102
  },
  {
    "month": "2016-09-01T00:00:00",
    "crime_category": "Violent",
    "count": 1298
  },
  {
    "month": "2016-10-01T00:00:00",
    "crime_category": "Other",
    "count": 9075
  },
  {
    "month": "2016-10-01T00:00:00",
    "crime_category": "Property",
    "count": 4081
  },
  {
    "month": "2016-10-01T00:00:00",
    "crime_category": "Violent",
    "count": 1355
  },
  {
    "month": "2016-11-01T00:00:00",
    "crime_category": "Other",
    "count": 7873
  },
  {
    "month": "2016-11-01T00:00:00",
    "crime_category": "Property",
    "count": 3669
  },
  {
    "month": "2016-11-01T00:00:00",
    "crime_category": "Violent",
    "count": 1296
  },
  {
    "month": "2016-12-01T00:00:00",
    "crime_category": "Other",
    "count": 7276
  },
  {
    "month": "2016-12-01T00:00:00",
    "crime_category": "Property",
    "count": 3634
  },
  {
    "month": "2016-12-01T00:00:00",
    "crime_category": "Violent",
    "count": 1232
  },
  {
    "month": "2017-01-01T00:00:00",
    "crime_category": "Other",
    "count": 7565
  },
  {
    "month": "2017-01-01T00:00:00",
    "crime_category": "Property",
    "count": 3447
  },
  {
    "month": "2017-01-01T00:00:00",
    "crime_category": "Violent",
    "count": 1292
  },
  {
    "month": "2017-02-01T00:00:00",
    "crime_category": "Other",
    "count": 7192
  },
  {
    "month": "2017-02-01T00:00:00",
    "crime_category": "Property",
    "count": 2974
  },
  {
    "month": "2017-02-01T00:00:00",
    "crime_category": "Violent",
    "count": 1105
  },
  {
    "month": "2017-03-01T00:00:00",
    "crime_category": "Other",
    "count": 8047
  },
  {
    "month": "2017-03-01T00:00:00",
    "crime_category": "Property",
    "count": 3183
  },
  {
    "month": "2017-03-01T00:00:00",
    "crime_category": "Violent",
    "count": 1077
  },
  {
    "month": "2017-04-01T00:00:00",
    "crime_category": "Other",
    "count": 8773
  },
  {
    "month": "2017-04-01T00:00:00",
    "crime_category": "Property",
    "count": 3373
  },
  {
    "month": "2017-04-01T00:00:00",
    "crime_category": "Violent",
    "count": 1216
  },
  {
    "month": "2017-05-01T00:00:00",
    "crime_category": "Other",
    "count": 9089
  },
  {
    "month": "2017-05-01T00:00:00",
    "crime_category": "Property",
    "count": 3977
  },
  {
    "month": "2017-05-01T00:00:00",
    "crime_category": "Violent",
    "count": 1298
  },
  {
    "month": "2017-06-01T00:00:00",
    "crime_category": "Other",
    "count": 9221
  },
  {
    "month": "2017-06-01T00:00:00",
    "crime_category": "Property",
    "count": 3995
  },
  {
    "month": "2017-06-01T00:00:00",
    "crime_category": "Violent",
    "count": 1349
  },
  {
    "month": "2017-07-01T00:00:00",
    "crime_category": "Other",
    "count": 9053
  },
  {
    "month": "2017-07-01T00:00:00",
    "crime_category": "Property",
    "count": 4150
  },
  {
    "month": "2017-07-01T00:00:00",
    "crime_category": "Violent",
    "count": 1374
  },
  {
    "month": "2017-08-01T00:00:00",
    "crime_category": "Other",
    "count": 8781
  },
  {
    "month": "2017-08-01T00:00:00",
    "crime_category": "Property",
    "count": 4293
  },
  {
    "month": "2017-08-01T00:00:00",
    "crime_category": "Violent",
    "count": 1320
  },
  {
    "month": "2017-09-01T00:00:00",
    "crime_category": "Other",
    "count": 8592
  },
  {
    "month": "2017-09-01T00:00:00",
    "crime_category": "Property",
    "count": 4081
  },
  {
    "month": "2017-09-01T00:00:00",
    "crime_category": "Violent",
    "count": 1299
  },
  {
    "month": "2017-10-01T00:00:00",
    "crime_category": "Other",
    "count": 8763
  },
  {
    "month": "2017-10-01T00:00:00",
    "crime_category": "Property",
    "count": 3842
  },
  {
    "month": "2017-10-01T00:00:00",
    "crime_category": "Violent",
    "count": 1356
  },
  {
    "month": "2017-11-01T00:00:00",
    "crime_category": "Other",
    "count": 7608
  },
  {
    "month": "2017-11-01T00:00:00",
    "crime_category": "Property",
    "count": 3592
  },
  {
    "month": "2017-11-01T00:00:00",
    "crime_category": "Violent",
    "count": 1249
  },
  {
    "month": "2017-12-01T00:00:00",
    "crime_category": "Other",
    "count": 6920
  },
  {
    "month": "2017-12-01T00:00:00",
    "crime_category": "Property",
    "count": 3383
  },
  {
    "month": "2017-12-01T00:00:00",
    "crime_category": "Violent",
    "count": 1153
  },
  {
    "month": "2018-01-01T00:00:00",
    "crime_category": "Other",
    "count": 7135
  },
  {
    "month": "2018-01-01T00:00:00",
    "crime_category": "Property",
    "count": 3362
  },
  {
    "month": "2018-01-01T00:00:00",
    "crime_category": "Violent",
    "count": 1181
  },
  {
    "month": "2018-02-01T00:00:00",
    "crime_category": "Other",
    "count": 7014
  },
  {
    "month": "2018-02-01T00:00:00",
    "crime_category": "Property",
    "count": 3098
  },
  {
    "month": "2018-02-01T00:00:00",
    "crime_category": "Violent",
    "count": 1024
  },
  {
    "month": "2018-03-01T00:00:00",
    "crime_category": "Other",
    "count": 7384
  },
  {
    "month": "2018-03-01T00:00:00",
    "crime_category": "Property",
    "count": 3086
  },
  {
    "month": "2018-03-01T00:00:00",
    "crime_category": "Violent",
    "count": 996
  },
  {
    "month": "2018-04-01T00:00:00",
    "crime_category": "Other",
    "count": 8346
  },
  {
    "month": "2018-04-01T00:00:00",
    "crime_category": "Property",
    "count": 3864
  },
  {
    "month": "2018-04-01T00:00:00",
    "crime_category": "Violent",
    "count": 1141
  },
  {
    "month": "2018-05-01T00:00:00",
    "crime_category": "Other",
    "count": 8834
  },
  {
    "month": "2018-05-01T00:00:00",
    "crime_category": "Property",
    "count": 3964
  },
  {
    "month": "2018-05-01T00:00:00",
    "crime_category": "Violent",
    "count": 1313
  },
  {
    "month": "2018-06-01T00:00:00",
    "crime_category": "Other",
    "count": 8743
  },
  {
    "month": "2018-06-01T00:00:00",
    "crime_category": "Property",
    "count": 3951
  },
  {
    "month": "2018-06-01T00:00:00",
    "crime_category": "Violent",
    "count": 1257
  },
  {
    "month": "2018-07-01T00:00:00",
    "crime_category": "Other",
    "count": 8645
  },
  {
    "month": "2018-07-01T00:00:00",
    "crime_category": "Property",
    "count": 4091
  },
  {
    "month": "2018-07-01T00:00:00",
    "crime_category": "Violent",
    "count": 1291
  },
  {
    "month": "2018-08-01T00:00:00",
    "crime_category": "Other",
    "count": 8554
  },
  {
    "month": "2018-08-01T00:00:00",
    "crime_category": "Property",
    "count": 4259
  },
  {
    "month": "2018-08-01T00:00:00",
    "crime_category": "Violent",
    "count": 1351
  },
  {
    "month": "2018-09-01T00:00:00",
    "crime_category": "Other",
    "count": 8172
  },
  {
    "month": "2018-09-01T00:00:00",
    "crime_category": "Property",
    "count": 4026
  },
  {
    "month": "2018-09-01T00:00:00",
    "crime_category": "Violent",
    "count": 1215
  },
  {
    "month": "2018-10-01T00:00:00",
    "crime_category": "Other",
    "count": 8205
  },
  {
    "month": "2018-10-01T00:00:00",
    "crime_category": "Property",
    "count": 4106
  },
  {
    "month": "2018-10-01T00:00:00",
    "crime_category": "Violent",
    "count": 1334
  },
  {
    "month": "2018-11-01T00:00:00",
    "crime_category": "Other",
    "count": 6875
  },
  {
    "month": "2018-11-01T00:00:00",
    "crime_category": "Property",
    "count": 3618
  },
  {
    "month": "2018-11-01T00:00:00",
    "crime_category": "Violent",
    "count": 1132
  },
  {
    "month": "2018-12-01T00:00:00",
    "crime_category": "Other",
    "count": 7045
  },
  {
    "month": "2018-12-01T00:00:00",
    "crime_category": "Property",
    "count": 3799
  },
  {
    "month": "2018-12-01T00:00:00",
    "crime_category": "Violent",
    "count": 1178
  },
  {
    "month": "2019-01-01T00:00:00",
    "crime_category": "Other",
    "count": 7435
  },
  {
    "month": "2019-01-01T00:00:00",
    "crime_category": "Property",
    "count": 3484
  },
  {
    "month": "2019-01-01T00:00:00",
    "crime_category": "Violent",
    "count": 1099
  },
  {
    "month": "2019-02-01T00:00:00",
    "crime_category": "Other",
    "count": 6681
  },
  {
    "month": "2019-02-01T00:00:00",
    "crime_category": "Property",
    "count": 3192
  },
  {
    "month": "2019-02-01T00:00:00",
    "crime_category": "Violent",
    "count": 1005
  },
  {
    "month": "2019-03-01T00:00:00",
    "crime_category": "Other",
    "count": 7794
  },
  {
    "month": "2019-03-01T00:00:00",
    "crime_category": "Property",
    "count": 3243
  },
  {
    "month": "2019-03-01T00:00:00",
    "crime_category": "Violent",
    "count": 1160
  },
  {
    "month": "2019-04-01T00:00:00",
    "crime_category": "Other",
    "count": 8590
  },
  {
    "month": "2019-04-01T00:00:00",
    "crime_category": "Property",
    "count": 3566
  },
  {
    "month": "2019-04-01T00:00:00",
    "crime_category": "Violent",
    "count": 1198
  },
  {
    "month": "2019-05-01T00:00:00",
    "crime_category": "Other",
    "count": 9241
  },
  {
    "month": "2019-05-01T00:00:00",
    "crime_category": "Property",
    "count": 3833
  },
  {
    "month": "2019-05-01T00:00:00",
    "crime_category": "Violent",
    "count": 1383
  },
  {
    "month": "2019-06-01T00:00:00",
    "crime_category": "Other",
    "count": 9256
  },
  {
    "month": "2019-06-01T00:00:00",
    "crime_category": "Property",
    "count": 3849
  },
  {
    "month": "2019-06-01T00:00:00",
    "crime_category": "Violent",
    "count": 1359
  },
  {
    "month": "2019-07-01T00:00:00",
    "crime_category": "Other",
    "count": 9632
  },
  {
    "month": "2019-07-01T00:00:00",
    "crime_category": "Property",
    "count": 4150
  },
  {
    "month": "2019-07-01T00:00:00",
    "crime_category": "Violent",
    "count": 1379
  },
  {
    "month": "2019-08-01T00:00:00",
    "crime_category": "Other",
    "count": 9478
  },
  {
    "month": "2019-08-01T00:00:00",
    "crime_category": "Property",
    "count": 4106
  },
  {
    "month": "2019-08-01T00:00:00",
    "crime_category": "Violent",
    "count": 1374
  },
  {
    "month": "2019-09-01T00:00:00",
    "crime_category": "Other",
    "count": 9033
  },
  {
    "month": "2019-09-01T00:00:00",
    "crime_category": "Property",
    "count": 4229
  },
  {
    "month": "2019-09-01T00:00:00",
    "crime_category": "Violent",
    "count": 1340
  },
  {
    "month": "2019-10-01T00:00:00",
    "crime_category": "Other",
    "count": 8675
  },
  {
    "month": "2019-10-01T00:00:00",
    "crime_category": "Property",
    "count": 4328
  },
  {
    "month": "2019-10-01T00:00:00",
    "crime_category": "Violent",
    "count": 1462
  },
  {
    "month": "2019-11-01T00:00:00",
    "crime_category": "Other",
    "count": 7217
  },
  {
    "month": "2019-11-01T00:00:00",
    "crime_category": "Property",
    "count": 3964
  },
  {
    "month": "2019-11-01T00:00:00",
    "crime_category": "Violent",
    "count": 1194
  },
  {
    "month": "2019-12-01T00:00:00",
    "crime_category": "Other",
    "count": 6898
  },
  {
    "month": "2019-12-01T00:00:00",
    "crime_category": "Property",
    "count": 4276
  },
  {
    "month": "2019-12-01T00:00:00",
    "crime_category": "Violent",
    "count": 1345
  },
  {
    "month": "2020-01-01T00:00:00",
    "crime_category": "Other",
    "count": 7604
  },
  {
    "month": "2020-01-01T00:00:00",
    "crime_category": "Property",
    "count": 4199
  },
  {
    "month": "2020-01-01T00:00:00",
    "crime_category": "Violent",
    "count": 1238
  },
  {
    "month": "2020-02-01T00:00:00",
    "crime_category": "Other",
    "count": 7655
  },
  {
    "month": "2020-02-01T00:00:00",
    "crime_category": "Property",
    "count": 3835
  },
  {
    "month": "2020-02-01T00:00:00",
    "crime_category": "Violent",
    "count": 1203
  },
  {
    "month": "2020-03-01T00:00:00",
    "crime_category": "Other",
    "count": 6602
  },
  {
    "month": "2020-03-01T00:00:00",
    "crime_category": "Property",
    "count": 3391
  },
  {
    "month": "2020-03-01T00:00:00",
    "crime_category": "Violent",
    "count": 1203
  },
  {
    "month": "2020-04-01T00:00:00",
    "crime_category": "Other",
    "count": 4828
  },
  {
    "month": "2020-04-01T00:00:00",
    "crime_category": "Property",
    "count": 3238
  },
  {
    "month": "2020-04-01T00:00:00",
    "crime_category": "Violent",
    "count": 957
  },
  {
    "month": "2020-05-01T00:00:00",
    "crime_category": "Other",
    "count": 7201
  },
  {
    "month": "2020-05-01T00:00:00",
    "crime_category": "Property",
    "count": 3745
  },
  {
    "month": "2020-05-01T00:00:00",
    "crime_category": "Violent",
    "count": 1184
  },
  {
    "month": "2020-06-01T00:00:00",
    "crime_category": "Other",
    "count": 5761
  },
  {
    "month": "2020-06-01T00:00:00",
    "crime_category": "Property",
    "count": 3763
  },
  {
    "month": "2020-06-01T00:00:00",
    "crime_category": "Violent",
    "count": 1283
  },
  {
    "month": "2020-07-01T00:00:00",
    "crime_category": "Other",
    "count": 6087
  },
  {
    "month": "2020-07-01T00:00:00",
    "crime_category": "Property",
    "count": 2926
  },
  {
    "month": "2020-07-01T00:00:00",
    "crime_category": "Violent",
    "count": 1241
  },
  {
    "month": "2020-08-01T00:00:00",
    "crime_category": "Other",
    "count": 6267
  },
  {
    "month": "2020-08-01T00:00:00",
    "crime_category": "Property",
    "count": 3190
  },
  {
    "month": "2020-08-01T00:00:00",
    "crime_category": "Violent",
    "count": 1458
  },
  {
    "month": "2020-09-01T00:00:00",
    "crime_category": "Other",
    "count": 6498
  },
  {
    "month": "2020-09-01T00:00:00",
    "crime_category": "Property",
    "count": 3399
  },
  {
    "month": "2020-09-01T00:00:00",
    "crime_category": "Violent",
    "count": 1394
  },
  {
    "month": "2020-10-01T00:00:00",
    "crime_category": "Other",
    "count": 6616
  },
  {
    "month": "2020-10-01T00:00:00",
    "crime_category": "Property",
    "count": 4375
  },
  {
    "month": "2020-10-01T00:00:00",
    "crime_category": "Violent",
    "count": 1644
  },
  {
    "month": "2020-11-01T00:00:00",
    "crime_category": "Other",
    "count": 5403
  },
  {
    "month": "2020-11-01T00:00:00",
    "crime_category": "Property",
    "count": 3408
  },
  {
    "month": "2020-11-01T00:00:00",
    "crime_category": "Violent",
    "count": 1322
  },
  {
    "month": "2020-12-01T00:00:00",
    "crime_category": "Other",
    "count": 5333
  },
  {
    "month": "2020-12-01T00:00:00",
    "crime_category": "Property",
    "count": 3720
  },
  {
    "month": "2020-12-01T00:00:00",
    "crime_category": "Violent",
    "count": 1240
  },
  {
    "month": "2021-01-01T00:00:00",
    "crime_category": "Other",
    "count": 5787
  },
  {
    "month": "2021-01-01T00:00:00",
    "crime_category": "Property",
    "count": 3911
  },
  {
    "month": "2021-01-01T00:00:00",
    "crime_category": "Violent",
    "count": 1336
  },
  {
    "month": "2021-02-01T00:00:00",
    "crime_category": "Other",
    "count": 5039
  },
  {
    "month": "2021-02-01T00:00:00",
    "crime_category": "Property",
    "count": 2652
  },
  {
    "month": "2021-02-01T00:00:00",
    "crime_category": "Violent",
    "count": 947
  },
  {
    "month": "2021-03-01T00:00:00",
    "crime_category": "Other",
    "count": 6031
  },
  {
    "month": "2021-03-01T00:00:00",
    "crime_category": "Property",
    "count": 3417
  },
  {
    "month": "2021-03-01T00:00:00",
    "crime_category": "Violent",
    "count": 1178
  },
  {
    "month": "2021-04-01T00:00:00",
    "crime_category": "Other",
    "count": 5829
  },
  {
    "month": "2021-04-01T00:00:00",
    "crime_category": "Property",
    "count": 3410
  },
  {
    "month": "2021-04-01T00:00:00",
    "crime_category": "Violent",
    "count": 1135
  },
  {
    "month": "2021-05-01T00:00:00",
    "crime_category": "Other",
    "count": 5931
  },
  {
    "month": "2021-05-01T00:00:00",
    "crime_category": "Property",
    "count": 3734
  },
  {
    "month": "2021-05-01T00:00:00",
    "crime_category": "Violent",
    "count": 1246
  },
  {
    "month": "2021-06-01T00:00:00",
    "crime_category": "Other",
    "count": 5959
  },
  {
    "month": "2021-06-01T00:00:00",
    "crime_category": "Property",
    "count": 3953
  },
  {
    "month": "2021-06-01T00:00:00",
    "crime_category": "Violent",
    "count": 1222
  },
  {
    "month": "2021-07-01T00:00:00",
    "crime_category": "Other",
    "count": 6290
  },
  {
    "month": "2021-07-01T00:00:00",
    "crime_category": "Property",
    "count": 4291
  },
  {
    "month": "2021-07-01T00:00:00",
    "crime_category": "Violent",
    "count": 1263
  },
  {
    "month": "2021-08-01T00:00:00",
    "crime_category": "Other",
    "count": 5928
  },
  {
    "month": "2021-08-01T00:00:00",
    "crime_category": "Property",
    "count": 4507
  },
  {
    "month": "2021-08-01T00:00:00",
    "crime_category": "Violent",
    "count": 1309
  },
  {
    "month": "2021-09-01T00:00:00",
    "crime_category": "Other",
    "count": 5892
  },
  {
    "month": "2021-09-01T00:00:00",
    "crime_category": "Property",
    "count": 4840
  },
  {
    "month": "2021-09-01T00:00:00",
    "crime_category": "Violent",
    "count": 1353
  },
  {
    "month": "2021-10-01T00:00:00",
    "crime_category": "Other",
    "count": 6284
  },
  {
    "month": "2021-10-01T00:00:00",
    "crime_category": "Property",
    "count": 5421
  },
  {
    "month": "2021-10-01T00:00:00",
    "crime_category": "Violent",
    "count": 1391
  },
  {
    "month": "2021-11-01T00:00:00",
    "crime_category": "Other",
    "count": 5402
  },
  {
    "month": "2021-11-01T00:00:00",
    "crime_category": "Property",
    "count": 4787
  },
  {
    "month": "2021-11-01T00:00:00",
    "crime_category": "Violent",
    "count": 1307
  },
  {
    "month": "2021-12-01T00:00:00",
    "crime_category": "Other",
    "count": 5138
  },
  {
    "month": "2021-12-01T00:00:00",
    "crime_category": "Property",
    "count": 4879
  },
  {
    "month": "2021-12-01T00:00:00",
    "crime_category": "Violent",
    "count": 1384
  },
  {
    "month": "2022-01-01T00:00:00",
    "crime_category": "Other",
    "count": 4748
  },
  {
    "month": "2022-01-01T00:00:00",
    "crime_category": "Property",
    "count": 4499
  },
  {
    "month": "2022-01-01T00:00:00",
    "crime_category": "Violent",
    "count": 1276
  },
  {
    "month": "2022-02-01T00:00:00",
    "crime_category": "Other",
    "count": 5107
  },
  {
    "month": "2022-02-01T00:00:00",
    "crime_category": "Property",
    "count": 4195
  },
  {
    "month": "2022-02-01T00:00:00",
    "crime_category": "Violent",
    "count": 1107
  },
  {
    "month": "2022-03-01T00:00:00",
    "crime_category": "Other",
    "count": 5875
  },
  {
    "month": "2022-03-01T00:00:00",
    "crime_category": "Property",
    "count": 4840
  },
  {
    "month": "2022-03-01T00:00:00",
    "crime_category": "Violent",
    "count": 1187
  },
  {
    "month": "2022-04-01T00:00:00",
    "crime_category": "Other",
    "count": 5959
  },
  {
    "month": "2022-04-01T00:00:00",
    "crime_category": "Property",
    "count": 4916
  },
  {
    "month": "2022-04-01T00:00:00",
    "crime_category": "Violent",
    "count": 1257
  },
  {
    "month": "2022-05-01T00:00:00",
    "crime_category": "Other",
    "count": 6360
  },
  {
    "month": "2022-05-01T00:00:00",
    "crime_category": "Property",
    "count": 5387
  },
  {
    "month": "2022-05-01T00:00:00",
    "crime_category": "Violent",
    "count": 1383
  },
  {
    "month": "2022-06-01T00:00:00",
    "crime_category": "Other",
    "count": 6203
  },
  {
    "month": "2022-06-01T00:00:00",
    "crime_category": "Property",
    "count": 5821
  },
  {
    "month": "2022-06-01T00:00:00",
    "crime_category": "Violent",
    "count": 1465
  },
  {
    "month": "2022-07-01T00:00:00",
    "crime_category": "Other",
    "count": 6266
  },
  {
    "month": "2022-07-01T00:00:00",
    "crime_category": "Property",
    "count": 6081
  },
  {
    "month": "2022-07-01T00:00:00",
    "crime_category": "Violent",
    "count": 1402
  },
  {
    "month": "2022-08-01T00:00:00",
    "crime_category": "Other",
    "count": 6270
  },
  {
    "month": "2022-08-01T00:00:00",
    "crime_category": "Property",
    "count": 6391
  },
  {
    "month": "2022-08-01T00:00:00",
    "crime_category": "Violent",
    "count": 1294
  },
  {
    "month": "2022-09-01T00:00:00",
    "crime_category": "Other",
    "count": 5865
  },
  {
    "month": "2022-09-01T00:00:00",
    "crime_category": "Property",
    "count": 6049
  },
  {
    "month": "2022-09-01T00:00:00",
    "crime_category": "Violent",
    "count": 1280
  },
  {
    "month": "2022-10-01T00:00:00",
    "crime_category": "Other",
    "count": 5788
  },
  {
    "month": "2022-10-01T00:00:00",
    "crime_category": "Property",
    "count": 6219
  },
  {
    "month": "2022-10-01T00:00:00",
    "crime_category": "Violent",
    "count": 1246
  },
  {
    "month": "2022-11-01T00:00:00",
    "crime_category": "Other",
    "count": 5665
  },
  {
    "month": "2022-11-01T00:00:00",
    "crime_category": "Property",
    "count": 5855
  },
  {
    "month": "2022-11-01T00:00:00",
    "crime_category": "Violent",
    "count": 1211
  },
  {
    "month": "2022-12-01T00:00:00",
    "crime_category": "Other",
    "count": 5482
  },
  {
    "month": "2022-12-01T00:00:00",
    "crime_category": "Property",
    "count": 6139
  },
  {
    "month": "2022-12-01T00:00:00",
    "crime_category": "Violent",
    "count": 1120
  },
  {
    "month": "2023-01-01T00:00:00",
    "crime_category": "Other",
    "count": 6092
  },
  {
    "month": "2023-01-01T00:00:00",
    "crime_category": "Property",
    "count": 6145
  },
  {
    "month": "2023-01-01T00:00:00",
    "crime_category": "Violent",
    "count": 1195
  },
  {
    "month": "2023-02-01T00:00:00",
    "crime_category": "Other",
    "count": 5588
  },
  {
    "month": "2023-02-01T00:00:00",
    "crime_category": "Property",
    "count": 5574
  },
  {
    "month": "2023-02-01T00:00:00",
    "crime_category": "Violent",
    "count": 1060
  },
  {
    "month": "2023-03-01T00:00:00",
    "crime_category": "Other",
    "count": 6537
  },
  {
    "month": "2023-03-01T00:00:00",
    "crime_category": "Property",
    "count": 6087
  },
  {
    "month": "2023-03-01T00:00:00",
    "crime_category": "Violent",
    "count": 1124
  },
  {
    "month": "2023-04-01T00:00:00",
    "crime_category": "Other",
    "count": 6519
  },
  {
    "month": "2023-04-01T00:00:00",
    "crime_category": "Property",
    "count": 6035
  },
  {
    "month": "2023-04-01T00:00:00",
    "crime_category": "Violent",
    "count": 1174
  },
  {
    "month": "2023-05-01T00:00:00",
    "crime_category": "Other",
    "count": 7064
  },
  {
    "month": "2023-05-01T00:00:00",
    "crime_category": "Property",
    "count": 6921
  },
  {
    "month": "2023-05-01T00:00:00",
    "crime_category": "Violent",
    "count": 1425
  },
  {
    "month": "2023-06-01T00:00:00",
    "crime_category": "Other",
    "count": 6760
  },
  {
    "month": "2023-06-01T00:00:00",
    "crime_category": "Property",
    "count": 7136
  },
  {
    "month": "2023-06-01T00:00:00",
    "crime_category": "Violent",
    "count": 1262
  },
  {
    "month": "2023-07-01T00:00:00",
    "crime_category": "Other",
    "count": 6703
  },
  {
    "month": "2023-07-01T00:00:00",
    "crime_category": "Property",
    "count": 7651
  },
  {
    "month": "2023-07-01T00:00:00",
    "crime_category": "Violent",
    "count": 1387
  },
  {
    "month": "2023-08-01T00:00:00",
    "crime_category": "Other",
    "count": 6708
  },
  {
    "month": "2023-08-01T00:00:00",
    "crime_category": "Property",
    "count": 7732
  },
  {
    "month": "2023-08-01T00:00:00",
    "crime_category": "Violent",
    "count": 1352
  },
  {
    "month": "2023-09-01T00:00:00",
    "crime_category": "Other",
    "count": 6299
  },
  {
    "month": "2023-09-01T00:00:00",
    "crime_category": "Property",
    "count": 6568
  },
  {
    "month": "2023-09-01T00:00:00",
    "crime_category": "Violent",
    "count": 1225
  },
  {
    "month": "2023-10-01T00:00:00",
    "crime_category": "Other",
    "count": 6191
  },
  {
    "month": "2023-10-01T00:00:00",
    "crime_category": "Property",
    "count": 6600
  },
  {
    "month": "2023-10-01T00:00:00",
    "crime_category": "Violent",
    "count": 1273
  },
  {
    "month": "2023-11-01T00:00:00",
    "crime_category": "Other",
    "count": 5827
  },
  {
    "month": "2023-11-01T00:00:00",
    "crime_category": "Property",
    "count": 5908
  },
  {
    "month": "2023-11-01T00:00:00",
    "crime_category": "Violent",
    "count": 1152
  },
  {
    "month": "2023-12-01T00:00:00",
    "crime_category": "Other",
    "count": 5860
  },
  {
    "month": "2023-12-01T00:00:00",
    "crime_category": "Property",
    "count": 5845
  },
  {
    "month": "2023-12-01T00:00:00",
    "crime_category": "Violent",
    "count": 1044
  },
  {
    "month": "2024-01-01T00:00:00",
    "crime_category": "Other",
    "count": 5733
  },
  {
    "month": "2024-01-01T00:00:00",
    "crime_category": "Property",
    "count": 5416
  },
  {
    "month": "2024-01-01T00:00:00",
    "crime_category": "Violent",
    "count": 1105
  },
  {
    "month": "2024-02-01T00:00:00",
    "crime_category": "Other",
    "count": 5977
  },
  {
    "month": "2024-02-01T00:00:00",
    "crime_category": "Property",
    "count": 4978
  },
  {
    "month": "2024-02-01T00:00:00",
    "crime_category": "Violent",
    "count": 959
  },
  {
    "month": "2024-03-01T00:00:00",
    "crime_category": "Other",
    "count": 5973
  },
  {
    "month": "2024-03-01T00:00:00",
    "crime_category": "Property",
    "count": 5387
  },
  {
    "month": "2024-03-01T00:00:00",
    "crime_category": "Violent",
    "count": 998
  },
  {
    "month": "2024-04-01T00:00:00",
    "crime_category": "Other",
    "count": 6218
  },
  {
    "month": "2024-04-01T00:00:00",
    "crime_category": "Property",
    "count": 5741
  },
  {
    "month": "2024-04-01T00:00:00",
    "crime_category": "Violent",
    "count": 1078
  },
  {
    "month": "2024-05-01T00:00:00",
    "crime_category": "Other",
    "count": 6729
  },
  {
    "month": "2024-05-01T00:00:00",
    "crime_category": "Property",
    "count": 6509
  },
  {
    "month": "2024-05-01T00:00:00",
    "crime_category": "Violent",
    "count": 1161
  },
  {
    "month": "2024-06-01T00:00:00",
    "crime_category": "Other",
    "count": 6579
  },
  {
    "month": "2024-06-01T00:00:00",
    "crime_category": "Property",
    "count": 6477
  },
  {
    "month": "2024-06-01T00:00:00",
    "crime_category": "Violent",
    "count": 1145
  },
  {
    "month": "2024-07-01T00:00:00",
    "crime_category": "Other",
    "count": 7201
  },
  {
    "month": "2024-07-01T00:00:00",
    "crime_category": "Property",
    "count": 6553
  },
  {
    "month": "2024-07-01T00:00:00",
    "crime_category": "Violent",
    "count": 1328
  },
  {
    "month": "2024-08-01T00:00:00",
    "crime_category": "Other",
    "count": 6777
  },
  {
    "month": "2024-08-01T00:00:00",
    "crime_category": "Property",
    "count": 6277
  },
  {
    "month": "2024-08-01T00:00:00",
    "crime_category": "Violent",
    "count": 1244
  },
  {
    "month": "2024-09-01T00:00:00",
    "crime_category": "Other",
    "count": 6702
  },
  {
    "month": "2024-09-01T00:00:00",
    "crime_category": "Property",
    "count": 5824
  },
  {
    "month": "2024-09-01T00:00:00",
    "crime_category": "Violent",
    "count": 1241
  },
  {
    "month": "2024-10-01T00:00:00",
    "crime_category": "Other",
    "count": 6496
  },
  {
    "month": "2024-10-01T00:00:00",
    "crime_category": "Property",
    "count": 6493
  },
  {
    "month": "2024-10-01T00:00:00",
    "crime_category": "Violent",
    "count": 1182
  },
  {
    "month": "2024-11-01T00:00:00",
    "crime_category": "Other",
    "count": 5861
  },
  {
    "month": "2024-11-01T00:00:00",
    "crime_category": "Property",
    "count": 5803
  },
  {
    "month": "2024-11-01T00:00:00",
    "crime_category": "Violent",
    "count": 1128
  },
  {
    "month": "2024-12-01T00:00:00",
    "crime_category": "Other",
    "count": 5636
  },
  {
    "month": "2024-12-01T00:00:00",
    "crime_category": "Property",
    "count": 5521
  },
  {
    "month": "2024-12-01T00:00:00",
    "crime_category": "Violent",
    "count": 959
  },
  {
    "month": "2025-01-01T00:00:00",
    "crime_category": "Other",
    "count": 5758
  },
  {
    "month": "2025-01-01T00:00:00",
    "crime_category": "Property",
    "count": 5296
  },
  {
    "month": "2025-01-01T00:00:00",
    "crime_category": "Violent",
    "count": 926
  },
  {
    "month": "2025-02-01T00:00:00",
    "crime_category": "Other",
    "count": 5214
  },
  {
    "month": "2025-02-01T00:00:00",
    "crime_category": "Property",
    "count": 4439
  },
  {
    "month": "2025-02-01T00:00:00",
    "crime_category": "Violent",
    "count": 839
  },
  {
    "month": "2025-03-01T00:00:00",
    "crime_category": "Other",
    "count": 5285
  },
  {
    "month": "2025-03-01T00:00:00",
    "crime_category": "Property",
    "count": 4395
  },
  {
    "month": "2025-03-01T00:00:00",
    "crime_category": "Violent",
    "count": 758
  },
  {
    "month": "2025-04-01T00:00:00",
    "crime_category": "Other",
    "count": 6285
  },
  {
    "month": "2025-04-01T00:00:00",
    "crime_category": "Property",
    "count": 5373
  },
  {
    "month": "2025-04-01T00:00:00",
    "crime_category": "Violent",
    "count": 954
  },
  {
    "month": "2025-05-01T00:00:00",
    "crime_category": "Other",
    "count": 6538
  },
  {
    "month": "2025-05-01T00:00:00",
    "crime_category": "Property",
    "count": 5583
  },
  {
    "month": "2025-05-01T00:00:00",
    "crime_category": "Violent",
    "count": 1065
  },
  {
    "month": "2025-06-01T00:00:00",
    "crime_category": "Other",
    "count": 6929
  },
  {
    "month": "2025-06-01T00:00:00",
    "crime_category": "Property",
    "count": 5967
  },
  {
    "month": "2025-06-01T00:00:00",
    "crime_category": "Violent",
    "count": 1107
  },
  {
    "month": "2025-07-01T00:00:00",
    "crime_category": "Other",
    "count": 6960
  },
  {
    "month": "2025-07-01T00:00:00",
    "crime_category": "Property",
    "count": 6305
  },
  {
    "month": "2025-07-01T00:00:00",
    "crime_category": "Violent",
    "count": 1173
  },
  {
    "month": "2025-08-01T00:00:00",
    "crime_category": "Other",
    "count": 6680
  },
  {
    "month": "2025-08-01T00:00:00",
    "crime_category": "Property",
    "count": 5833
  },
  {
    "month": "2025-08-01T00:00:00",
    "crime_category": "Violent",
    "count": 1078
  },
  {
    "month": "2025-09-01T00:00:00",
    "crime_category": "Other",
    "count": 6851
  },
  {
    "month": "2025-09-01T00:00:00",
    "crime_category": "Property",
    "count": 6116
  },
  {
    "month": "2025-09-01T00:00:00",
    "crime_category": "Violent",
    "count": 1106
  },
  {
    "month": "2025-10-01T00:00:00",
    "crime_category": "Other",
    "count": 6694
  },
  {
    "month": "2025-10-01T00:00:00",
    "crime_category": "Property",
    "count": 6016
  },
  {
    "month": "2025-10-01T00:00:00",
    "crime_category": "Violent",
    "count": 1117
  },
  {
    "month": "2025-11-01T00:00:00",
    "crime_category": "Other",
    "count": 5895
  },
  {
    "month": "2025-11-01T00:00:00",
    "crime_category": "Property",
    "count": 5493
  },
  {
    "month": "2025-11-01T00:00:00",
    "crime_category": "Violent",
    "count": 987
  },
  {
    "month": "2025-12-01T00:00:00",
    "crime_category": "Other",
    "count": 5700
  },
  {
    "month": "2025-12-01T00:00:00",
    "crime_category": "Property",
    "count": 4924
  },
  {
    "month": "2025-12-01T00:00:00",
    "crime_category": "Violent",
    "count": 912
  },
  {
    "month": "2026-01-01T00:00:00",
    "crime_category": "Other",
    "count": 3712
  },
  {
    "month": "2026-01-01T00:00:00",
    "crime_category": "Property",
    "count": 3266
  },
  {
    "month": "2026-01-01T00:00:00",
    "crime_category": "Violent",
    "count": 565
  }
]